DearPyGui_DragAndDrop/__init__.py
DearPyGui_DragAndDrop/main.py
DearPyGui_DragAndDrop/setup.py
DearPyGui_DragAndDrop/tools.py
DearPyGui_DragAndDrop-1.0.0.dist-info/LICENSE
DearPyGui_DragAndDrop-1.0.0.dist-info/METADATA
DearPyGui_DragAndDrop-1.0.0.dist-info/WHEEL
DearPyGui_DragAndDrop-1.0.0.dist-info/top_level.txt
DearPyGui_DragAndDrop-1.0.0.dist-info/RECORD
