Metadata-Version: 2.1
Name: DearPyGui-DragAndDrop
Version: 1.0.0
Summary: Working Drag-and-Drop for DearPyGui, Windows only
Author: Ivan Nazaruk
License: MIT
Project-URL: Homepage, https://github.com/IvanNazaruk/DearPyGui-DragAndDrop
Project-URL: Bug Tracker, https://github.com/IvanNazaruk/DearPyGui-DragAndDrop/issues
Classifier: Intended Audience :: Developers
Classifier: License :: OSI Approved :: MIT License
Classifier: Programming Language :: Python :: 3
Classifier: Operating System :: Microsoft :: Windows
Requires-Python: >=3.7
License-File: LICENSE
Requires-Dist: pywin32
Requires-Dist: dearpygui (>=1.4)
